README.rst
setup.py
bin/teleloisirs
pyteleloisirs/__init__.py
pyteleloisirs/pyteleloisirs.py
pyteleloisirs.egg-info/PKG-INFO
pyteleloisirs.egg-info/SOURCES.txt
pyteleloisirs.egg-info/dependency_links.txt
pyteleloisirs.egg-info/requires.txt
pyteleloisirs.egg-info/top_level.txt